agents/__init__.py
agents/base.py
agents/config.py
agents/mcp_client.py
agents/registry.py
agents/tool_registry.py
agents/yaml_to_registry.py
agents/a2a/__init__.py
agents/a2a/agent.py
agents/a2a/card.py
agents/a2a/client.py
agents/a2a/server.py
agents/execution/__init__.py
agents/execution/backends.py
agents/execution/runner.py
evaluation/__init__.py
evaluation/harness.py
evaluation/metrics.py
evaluation/reporters.py
evaluation/runner.py
experiments/__init__.py
experiments/ab_testing.py
experiments/feature_flags.py
experiments/mlflow_integration.py
experiments/tracker.py
infra/__init__.py
memory/__init__.py
memory/agents.py
memory/context.py
memory/embeddings.py
memory/graphs.py
memory/manager.py
memory/policies.py
memory/shared.py
memory/stores.py
memory/strategies.py
monitoring/__init__.py
monitoring/alerting.py
monitoring/health_check.py
monitoring/metrics_collector.py
monitoring/performance.py
optimization/__init__.py
optimization/ab_testing.py
optimization/dspy_optimizer.py
optimization/prompt_optimizer.py
optimization/textgrad_optimizer.py
orchestration/langgraph/__init__.py
orchestration/langgraph/adapters.py
orchestration/langgraph/examples.py
orchestration/langgraph/nodes.py
orchestration/langgraph/workflow.py
reasoning/__init__.py
reasoning/distillation.py
reasoning/feedback.py
reasoning/optimizer.py
reasoning/policies.py
reasoning/trajectory.py
reasoning/tuner.py
services/__init__.py
services/api.py
services/websocket.py
services/worker.py
shared/__init__.py
shared/config_loader.py
shared/adapters/__init__.py
shared/adapters/base.py
shared/adapters/examples.py
shared/adapters/loader.py
shared/adapters/transaction_adapters.py
shared/schemas/__init__.py
shared/schemas/agent_io.py
shared/schemas/contexts.py
shared/schemas/embeddings.py
shared/schemas/evaluation.py
shared/schemas/examples.py
shared/schemas/fraud_signals.py
shared/schemas/learning.py
shared/schemas/mcp_tools.py
shared/schemas/nested_transaction.py
shared/schemas/optimization.py
sota_agent_framework-0.4.1.dist-info/licenses/LICENSE
sota_agent_framework-0.4.1.dist-info/METADATA
sota_agent_framework-0.4.1.dist-info/WHEEL
sota_agent_framework-0.4.1.dist-info/entry_points.txt
sota_agent_framework-0.4.1.dist-info/top_level.txt
sota_agent_framework-0.4.1.dist-info/RECORD
