Metadata-Version: 2.4
Name: sota-agent-framework
Version: 0.4.1
Summary: Domain-agnostic agent framework for integrating AI agents into data pipelines
Author: SOTA Agent Team
License: MIT
Project-URL: Homepage, https://github.com/your-org/sota-agent-framework
Project-URL: Documentation, https://github.com/your-org/sota-agent-framework/tree/main/docs
Project-URL: Repository, https://github.com/your-org/sota-agent-framework
Project-URL: Issues, https://github.com/your-org/sota-agent-framework/issues
Keywords: agents,agentic-ai,databricks,mlops,llm,framework,agent-orchestration,plug-and-play
Classifier: Development Status :: 3 - Alpha
Classifier: Intended Audience :: Developers
Classifier: Topic :: Software Development :: Libraries :: Application Frameworks
Classifier: Topic :: Scientific/Engineering :: Artificial Intelligence
Classifier: Programming Language :: Python :: 3
Classifier: Programming Language :: Python :: 3.9
Classifier: Programming Language :: Python :: 3.10
Classifier: Programming Language :: Python :: 3.11
Classifier: License :: OSI Approved :: MIT License
Classifier: Operating System :: OS Independent
Requires-Python: >=3.9
License-File: LICENSE
Requires-Dist: pydantic<3.0.0,>=2.0.0
Requires-Dist: pydantic-settings>=2.0.0
Requires-Dist: pyyaml>=6.0
Requires-Dist: httpx>=0.25.0
Requires-Dist: packaging>=23.0
Provides-Extra: databricks
Requires-Dist: databricks-sdk>=0.20.0; extra == "databricks"
Requires-Dist: databricks-sql-connector>=3.0.0; extra == "databricks"
Requires-Dist: mlflow>=2.10.0; extra == "databricks"
Provides-Extra: agent-frameworks
Requires-Dist: langgraph>=0.2.0; extra == "agent-frameworks"
Requires-Dist: langchain>=0.2.0; extra == "agent-frameworks"
Requires-Dist: langchain-core>=0.2.0; extra == "agent-frameworks"
Provides-Extra: optimization
Requires-Dist: dspy-ai>=2.4.0; extra == "optimization"
Requires-Dist: textgrad>=0.1.0; extra == "optimization"
Provides-Extra: ray
Requires-Dist: ray[default]>=2.0.0; extra == "ray"
Provides-Extra: mcp
Requires-Dist: mcp>=0.1.0; extra == "mcp"
Provides-Extra: a2a
Requires-Dist: a2a-sdk>=0.3.0; extra == "a2a"
Provides-Extra: semantic-search
Requires-Dist: sentence-transformers>=2.2.0; extra == "semantic-search"
Provides-Extra: messaging
Requires-Dist: nats-py>=2.6.0; extra == "messaging"
Requires-Dist: redis>=5.0.0; extra == "messaging"
Provides-Extra: telemetry
Requires-Dist: opentelemetry-api>=1.20.0; extra == "telemetry"
Requires-Dist: opentelemetry-sdk>=1.20.0; extra == "telemetry"
Requires-Dist: opentelemetry-instrumentation>=0.41b0; extra == "telemetry"
Provides-Extra: web
Requires-Dist: fastapi>=0.100.0; extra == "web"
Requires-Dist: uvicorn[standard]>=0.23.0; extra == "web"
Requires-Dist: websockets>=12.0; extra == "web"
Provides-Extra: monitoring
Requires-Dist: psutil>=5.9.0; extra == "monitoring"
Provides-Extra: ui
Requires-Dist: plotly>=5.0.0; extra == "ui"
Requires-Dist: gradio>=4.0.0; extra == "ui"
Requires-Dist: ipython>=8.0.0; extra == "ui"
Provides-Extra: documents
Requires-Dist: PyPDF2>=3.0.0; extra == "documents"
Requires-Dist: python-docx>=0.8.11; extra == "documents"
Provides-Extra: all
Requires-Dist: sota-agent-framework[a2a,agent-frameworks,databricks,documents,mcp,messaging,monitoring,optimization,ray,semantic-search,telemetry,ui,web]; extra == "all"
Provides-Extra: dev
Requires-Dist: pytest>=7.4.0; extra == "dev"
Requires-Dist: pytest-asyncio>=0.21.0; extra == "dev"
Requires-Dist: pytest-cov>=4.1.0; extra == "dev"
Requires-Dist: black>=23.0.0; extra == "dev"
Requires-Dist: ruff>=0.1.0; extra == "dev"
Requires-Dist: mypy>=1.5.0; extra == "dev"
Requires-Dist: ipython>=8.12.0; extra == "dev"
Requires-Dist: jupyter>=1.0.0; extra == "dev"
Dynamic: license-file
